landmark/__init__.py
landmark_detection-0.1.1.dist-info/METADATA
landmark_detection-0.1.1.dist-info/WHEEL
landmark_detection-0.1.1.dist-info/top_level.txt
landmark_detection-0.1.1.dist-info/RECORD
