Metadata-Version: 2.1
Name: landmark-detection
Version: 0.1.1
Summary: This is for detect coordinates parts of the body
Home-page: UNKNOWN
Author: Mahmoud kouwis
Author-email: <kouwiss.jr@gmail.com>
License: UNKNOWN
Keywords: python,opencv,mediapipe,detection,landmarks
Platform: UNKNOWN
Classifier: Development Status :: 1 - Planning
Classifier: Intended Audience :: Developers
Classifier: Programming Language :: Python :: 3
Classifier: Operating System :: Unix
Classifier: Operating System :: MacOS :: MacOS X
Classifier: Operating System :: Microsoft :: Windows
Requires-Dist: mediapipe
Requires-Dist: opencv-python
